pypersonality/__init__.py
pypersonality/personality.py
pypersonality/models/IntroExtro.pickle
pypersonality/models/IntuitionSensing.pickle
pypersonality/models/JudgingPercieiving.pickle
pypersonality/models/ThinkingFeeling.pickle
pypersonality/models/__init__.py
pypersonality-0.0.4.dist-info/WHEEL
pypersonality-0.0.4.dist-info/METADATA
pypersonality-0.0.4.dist-info/RECORD
